src/__init__.py
src/version_check.py
roa_ai_model-1.0.0.dist-info/LICENSE
roa_ai_model-1.0.0.dist-info/METADATA
roa_ai_model-1.0.0.dist-info/WHEEL
roa_ai_model-1.0.0.dist-info/top_level.txt
roa_ai_model-1.0.0.dist-info/RECORD
