Metadata-Version: 2.1
Name: roa-ai-model
Version: 1.0.0
Summary: ROA ML/DL modeling package
Home-page: https://github.com/roa-ai/roa_ai_model
Author: roa
Author-email: dev@roa.ai
License: UNKNOWN
Platform: UNKNOWN
Classifier: Programming Language :: Python :: 3
Classifier: License :: OSI Approved :: MIT License
Classifier: Operating System :: OS Independent
Requires-Dist: pandas
Requires-Dist: numpy
